{"_format":"","paths":{"artifacts":"out","build_infos":"out/build-info","sources":"src","tests":"test","scripts":"script","libraries":["lib"]},"files":{"lib/forge-std/src/Base.sol":{"lastModificationDate":1751349320645,"contentHash":"26ab04949780bbaec40dfa66ddea6aac","interfaceReprHash":null,"sourceName":"lib/forge-std/src/Base.sol","imports":["lib/forge-std/src/StdStorage.sol","lib/forge-std/src/Vm.sol"],"versionRequirement":">=0.6.2, <0.9.0","artifacts":{"CommonBase":{"0.8.29":{"default":{"path":"Base.sol/CommonBase.json","build_id":"4cb8066a7341661fda31173d8462bae1"}}},"ScriptBase":{"0.8.29":{"default":{"path":"Base.sol/ScriptBase.json","build_id":"4cb8066a7341661fda31173d8462bae1"}}},"TestBase":{"0.8.29":{"default":{"path":"Base.sol/TestBase.json","build_id":"4cb8066a7341661fda31173d8462bae1"}}}},"seenByCompiler":true},"lib/forge-std/src/Script.sol":{"lastModificationDate":1751349320645,"contentHash":"1d11dd99b6b917f2de20017e94d9de06","interfaceReprHash":null,"sourceName":"lib/forge-std/src/Script.sol","imports":["lib/forge-std/src/Base.sol","lib/forge-std/src/StdChains.sol","lib/forge-std/src/StdCheats.sol","lib/forge-std/src/StdConstants.sol","lib/forge-std/src/StdJson.sol","lib/forge-std/src/StdMath.sol","lib/forge-std/src/StdStorage.sol","lib/forge-std/src/StdStyle.sol","lib/forge-std/src/StdUtils.sol","lib/forge-std/src/Vm.sol","lib/forge-std/src/console.sol","lib/forge-std/src/console2.sol","lib/forge-std/src/interfaces/IMulticall3.sol","lib/forge-std/src/safeconsole.sol"],"versionRequirement":">=0.6.2, <0.9.0","artifacts":{"Script":{"0.8.29":{"default":{"path":"Script.sol/Script.json","build_id":"4cb8066a7341661fda31173d8462bae1"}}}},"seenByCompiler":true},"lib/forge-std/src/StdChains.sol":{"lastModificationDate":1751349320645,"contentHash":"46c326449920147b8c9f2114981019a1","interfaceReprHash":null,"sourceName":"lib/forge-std/src/StdChains.sol","imports":["lib/forge-std/src/Vm.sol"],"versionRequirement":">=0.6.2, <0.9.0","artifacts":{"StdChains":{"0.8.29":{"default":{"path":"StdChains.sol/StdChains.json","build_id":"4cb8066a7341661fda31173d8462bae1"}}}},"seenByCompiler":true},"lib/forge-std/src/StdCheats.sol":{"lastModificationDate":1751349320645,"contentHash":"88408106c41697153142f6a6eeb06728","interfaceReprHash":null,"sourceName":"lib/forge-std/src/StdCheats.sol","imports":["lib/forge-std/src/StdStorage.sol","lib/forge-std/src/Vm.sol","lib/forge-std/src/console.sol","lib/forge-std/src/console2.sol"],"versionRequirement":">=0.6.2, <0.9.0","artifacts":{"StdCheats":{"0.8.29":{"default":{"path":"StdCheats.sol/StdCheats.json","build_id":"4cb8066a7341661fda31173d8462bae1"}}},"StdCheatsSafe":{"0.8.29":{"default":{"path":"StdCheats.sol/StdCheatsSafe.json","build_id":"4cb8066a7341661fda31173d8462bae1"}}}},"seenByCompiler":true},"lib/forge-std/src/StdConstants.sol":{"lastModificationDate":1751349320645,"contentHash":"14edb96ae3a9171cd6885d775e077b2b","interfaceReprHash":null,"sourceName":"lib/forge-std/src/StdConstants.sol","imports":["lib/forge-std/src/Vm.sol","lib/forge-std/src/interfaces/IMulticall3.sol"],"versionRequirement":">=0.6.2, <0.9.0","artifacts":{"StdConstants":{"0.8.29":{"default":{"path":"StdConstants.sol/StdConstants.json","build_id":"4cb8066a7341661fda31173d8462bae1"}}}},"seenByCompiler":true},"lib/forge-std/src/StdJson.sol":{"lastModificationDate":1751349320645,"contentHash":"02209da5708eaee03e24a9c24a687370","interfaceReprHash":null,"sourceName":"lib/forge-std/src/StdJson.sol","imports":["lib/forge-std/src/Vm.sol"],"versionRequirement":">=0.6.0, <0.9.0","artifacts":{"stdJson":{"0.8.29":{"default":{"path":"StdJson.sol/stdJson.json","build_id":"4cb8066a7341661fda31173d8462bae1"}}}},"seenByCompiler":true},"lib/forge-std/src/StdMath.sol":{"lastModificationDate":1751349320645,"contentHash":"9da8f453eba6bb98f3d75bc6822bfb29","interfaceReprHash":null,"sourceName":"lib/forge-std/src/StdMath.sol","imports":[],"versionRequirement":">=0.6.2, <0.9.0","artifacts":{"stdMath":{"0.8.29":{"default":{"path":"StdMath.sol/stdMath.json","build_id":"4cb8066a7341661fda31173d8462bae1"}}}},"seenByCompiler":true},"lib/forge-std/src/StdStorage.sol":{"lastModificationDate":1751349320645,"contentHash":"ce68f6e336944f16d31351a47d0b19b8","interfaceReprHash":null,"sourceName":"lib/forge-std/src/StdStorage.sol","imports":["lib/forge-std/src/Vm.sol"],"versionRequirement":">=0.6.2, <0.9.0","artifacts":{"stdStorage":{"0.8.29":{"default":{"path":"StdStorage.sol/stdStorage.json","build_id":"4cb8066a7341661fda31173d8462bae1"}}},"stdStorageSafe":{"0.8.29":{"default":{"path":"StdStorage.sol/stdStorageSafe.json","build_id":"4cb8066a7341661fda31173d8462bae1"}}}},"seenByCompiler":true},"lib/forge-std/src/StdStyle.sol":{"lastModificationDate":1751349320645,"contentHash":"6281165a12aa639705c691fccefd855e","interfaceReprHash":null,"sourceName":"lib/forge-std/src/StdStyle.sol","imports":["lib/forge-std/src/Vm.sol"],"versionRequirement":">=0.4.22, <0.9.0","artifacts":{"StdStyle":{"0.8.29":{"default":{"path":"StdStyle.sol/StdStyle.json","build_id":"4cb8066a7341661fda31173d8462bae1"}}}},"seenByCompiler":true},"lib/forge-std/src/StdUtils.sol":{"lastModificationDate":1751349320646,"contentHash":"4c104fcdec12d3b28348ff9e32c1e4eb","interfaceReprHash":null,"sourceName":"lib/forge-std/src/StdUtils.sol","imports":["lib/forge-std/src/Vm.sol","lib/forge-std/src/interfaces/IMulticall3.sol"],"versionRequirement":">=0.6.2, <0.9.0","artifacts":{"StdUtils":{"0.8.29":{"default":{"path":"StdUtils.sol/StdUtils.json","build_id":"4cb8066a7341661fda31173d8462bae1"}}}},"seenByCompiler":true},"lib/forge-std/src/Vm.sol":{"lastModificationDate":1751349320695,"contentHash":"c89e8ba7ee46cc706870d539a13386b7","interfaceReprHash":null,"sourceName":"lib/forge-std/src/Vm.sol","imports":[],"versionRequirement":">=0.6.2, <0.9.0","artifacts":{"Vm":{"0.8.29":{"default":{"path":"Vm.sol/Vm.json","build_id":"4cb8066a7341661fda31173d8462bae1"}}},"VmSafe":{"0.8.29":{"default":{"path":"Vm.sol/VmSafe.json","build_id":"4cb8066a7341661fda31173d8462bae1"}}}},"seenByCompiler":true},"lib/forge-std/src/console.sol":{"lastModificationDate":1751349320646,"contentHash":"ce19a9e49945b42118379ff99d853c05","interfaceReprHash":null,"sourceName":"lib/forge-std/src/console.sol","imports":[],"versionRequirement":">=0.4.22, <0.9.0","artifacts":{"console":{"0.8.29":{"default":{"path":"console.sol/console.json","build_id":"4cb8066a7341661fda31173d8462bae1"}}}},"seenByCompiler":true},"lib/forge-std/src/console2.sol":{"lastModificationDate":1751349320646,"contentHash":"f65ad21034b111e70fb5342d5771efcd","interfaceReprHash":null,"sourceName":"lib/forge-std/src/console2.sol","imports":["lib/forge-std/src/console.sol"],"versionRequirement":">=0.4.22, <0.9.0","artifacts":{},"seenByCompiler":true},"lib/forge-std/src/interfaces/IMulticall3.sol":{"lastModificationDate":1751349320647,"contentHash":"7b131ca1ca32ef6378b7b9ad5488b901","interfaceReprHash":null,"sourceName":"lib/forge-std/src/interfaces/IMulticall3.sol","imports":[],"versionRequirement":">=0.6.2, <0.9.0","artifacts":{"IMulticall3":{"0.8.29":{"default":{"path":"IMulticall3.sol/IMulticall3.json","build_id":"4cb8066a7341661fda31173d8462bae1"}}}},"seenByCompiler":true},"lib/forge-std/src/safeconsole.sol":{"lastModificationDate":1751349320647,"contentHash":"1445aa2f47000e212173e0cefd6c7a77","interfaceReprHash":null,"sourceName":"lib/forge-std/src/safeconsole.sol","imports":[],"versionRequirement":">=0.6.2, <0.9.0","artifacts":{"safeconsole":{"0.8.29":{"default":{"path":"safeconsole.sol/safeconsole.json","build_id":"4cb8066a7341661fda31173d8462bae1"}}}},"seenByCompiler":true},"node_modules/@switchboard-xyz/on-demand-solidity/ISwitchboard.sol":{"lastModificationDate":1747252655969,"contentHash":"ebc98102c04c296e39329932c815b617","interfaceReprHash":null,"sourceName":"node_modules/@switchboard-xyz/on-demand-solidity/ISwitchboard.sol","imports":["node_modules/@switchboard-xyz/on-demand-solidity/interfaces/IAggregatorModule.sol","node_modules/@switchboard-xyz/on-demand-solidity/interfaces/IOracleModule.sol","node_modules/@switchboard-xyz/on-demand-solidity/interfaces/IQueueModule.sol","node_modules/@switchboard-xyz/on-demand-solidity/interfaces/IRandomnessModule.sol","node_modules/@switchboard-xyz/on-demand-solidity/interfaces/ISwitchboardModule.sol","node_modules/@switchboard-xyz/on-demand-solidity/structs/Structs.sol"],"versionRequirement":">=0.8.0, <0.9.0","artifacts":{"ISwitchboard":{"0.8.29":{"default":{"path":"ISwitchboard.sol/ISwitchboard.json","build_id":"4cb8066a7341661fda31173d8462bae1"}}}},"seenByCompiler":true},"node_modules/@switchboard-xyz/on-demand-solidity/interfaces/IAggregatorModule.sol":{"lastModificationDate":1747252655968,"contentHash":"62e002646ff3d139b642d8d71cc756fd","interfaceReprHash":null,"sourceName":"node_modules/@switchboard-xyz/on-demand-solidity/interfaces/IAggregatorModule.sol","imports":["node_modules/@switchboard-xyz/on-demand-solidity/structs/Structs.sol"],"versionRequirement":">=0.8.0, <0.9.0","artifacts":{"IAggregatorModule":{"0.8.29":{"default":{"path":"IAggregatorModule.sol/IAggregatorModule.json","build_id":"4cb8066a7341661fda31173d8462bae1"}}}},"seenByCompiler":true},"node_modules/@switchboard-xyz/on-demand-solidity/interfaces/IOracleModule.sol":{"lastModificationDate":1747252655968,"contentHash":"eebc38c207d5575381198146cfbe0da5","interfaceReprHash":null,"sourceName":"node_modules/@switchboard-xyz/on-demand-solidity/interfaces/IOracleModule.sol","imports":["node_modules/@switchboard-xyz/on-demand-solidity/structs/Structs.sol"],"versionRequirement":">=0.8.0, <0.9.0","artifacts":{"IOracleModule":{"0.8.29":{"default":{"path":"IOracleModule.sol/IOracleModule.json","build_id":"4cb8066a7341661fda31173d8462bae1"}}}},"seenByCompiler":true},"node_modules/@switchboard-xyz/on-demand-solidity/interfaces/IQueueModule.sol":{"lastModificationDate":1747252655968,"contentHash":"22331427db078ea82d1af4227225bc15","interfaceReprHash":null,"sourceName":"node_modules/@switchboard-xyz/on-demand-solidity/interfaces/IQueueModule.sol","imports":["node_modules/@switchboard-xyz/on-demand-solidity/structs/Structs.sol"],"versionRequirement":">=0.8.0, <0.9.0","artifacts":{"IQueueModule":{"0.8.29":{"default":{"path":"IQueueModule.sol/IQueueModule.json","build_id":"4cb8066a7341661fda31173d8462bae1"}}}},"seenByCompiler":true},"node_modules/@switchboard-xyz/on-demand-solidity/interfaces/IRandomnessModule.sol":{"lastModificationDate":1747252655969,"contentHash":"e634454cd374f90318060f7d22089058","interfaceReprHash":null,"sourceName":"node_modules/@switchboard-xyz/on-demand-solidity/interfaces/IRandomnessModule.sol","imports":["node_modules/@switchboard-xyz/on-demand-solidity/structs/Structs.sol"],"versionRequirement":">=0.8.0, <0.9.0","artifacts":{"IRandomnessModule":{"0.8.29":{"default":{"path":"IRandomnessModule.sol/IRandomnessModule.json","build_id":"4cb8066a7341661fda31173d8462bae1"}}}},"seenByCompiler":true},"node_modules/@switchboard-xyz/on-demand-solidity/interfaces/ISwitchboardModule.sol":{"lastModificationDate":1747252655969,"contentHash":"f9f54bcb7f31afeacb9027fe41ce54d7","interfaceReprHash":null,"sourceName":"node_modules/@switchboard-xyz/on-demand-solidity/interfaces/ISwitchboardModule.sol","imports":["node_modules/@switchboard-xyz/on-demand-solidity/structs/Structs.sol"],"versionRequirement":">=0.8.0, <0.9.0","artifacts":{"ISwitchboardModule":{"0.8.29":{"default":{"path":"ISwitchboardModule.sol/ISwitchboardModule.json","build_id":"4cb8066a7341661fda31173d8462bae1"}}}},"seenByCompiler":true},"node_modules/@switchboard-xyz/on-demand-solidity/structs/Structs.sol":{"lastModificationDate":1747252655969,"contentHash":"4597cdb79af9198af549ec0a260dd1a7","interfaceReprHash":null,"sourceName":"node_modules/@switchboard-xyz/on-demand-solidity/structs/Structs.sol","imports":[],"versionRequirement":">=0.8.0, <0.9.0","artifacts":{"Structs":{"0.8.29":{"default":{"path":"Structs.sol/Structs.json","build_id":"4cb8066a7341661fda31173d8462bae1"}}}},"seenByCompiler":true},"script/Deploy.s.sol":{"lastModificationDate":1751348972442,"contentHash":"0c3b1138c1235f6343a9f3e477d817c0","interfaceReprHash":null,"sourceName":"script/Deploy.s.sol","imports":["lib/forge-std/src/Base.sol","lib/forge-std/src/Script.sol","lib/forge-std/src/StdChains.sol","lib/forge-std/src/StdCheats.sol","lib/forge-std/src/StdConstants.sol","lib/forge-std/src/StdJson.sol","lib/forge-std/src/StdMath.sol","lib/forge-std/src/StdStorage.sol","lib/forge-std/src/StdStyle.sol","lib/forge-std/src/StdUtils.sol","lib/forge-std/src/Vm.sol","lib/forge-std/src/console.sol","lib/forge-std/src/console2.sol","lib/forge-std/src/interfaces/IMulticall3.sol","lib/forge-std/src/safeconsole.sol","node_modules/@switchboard-xyz/on-demand-solidity/ISwitchboard.sol","node_modules/@switchboard-xyz/on-demand-solidity/interfaces/IAggregatorModule.sol","node_modules/@switchboard-xyz/on-demand-solidity/interfaces/IOracleModule.sol","node_modules/@switchboard-xyz/on-demand-solidity/interfaces/IQueueModule.sol","node_modules/@switchboard-xyz/on-demand-solidity/interfaces/IRandomnessModule.sol","node_modules/@switchboard-xyz/on-demand-solidity/interfaces/ISwitchboardModule.sol","node_modules/@switchboard-xyz/on-demand-solidity/structs/Structs.sol","src/Example.sol"],"versionRequirement":"^0.8.0","artifacts":{"DeployScript":{"0.8.29":{"default":{"path":"Deploy.s.sol/DeployScript.json","build_id":"4cb8066a7341661fda31173d8462bae1"}}}},"seenByCompiler":true},"src/Example.sol":{"lastModificationDate":1751348081294,"contentHash":"639cb8e333a348df99c2c2ea72a59e50","interfaceReprHash":null,"sourceName":"src/Example.sol","imports":["node_modules/@switchboard-xyz/on-demand-solidity/ISwitchboard.sol","node_modules/@switchboard-xyz/on-demand-solidity/interfaces/IAggregatorModule.sol","node_modules/@switchboard-xyz/on-demand-solidity/interfaces/IOracleModule.sol","node_modules/@switchboard-xyz/on-demand-solidity/interfaces/IQueueModule.sol","node_modules/@switchboard-xyz/on-demand-solidity/interfaces/IRandomnessModule.sol","node_modules/@switchboard-xyz/on-demand-solidity/interfaces/ISwitchboardModule.sol","node_modules/@switchboard-xyz/on-demand-solidity/structs/Structs.sol"],"versionRequirement":"^0.8.0","artifacts":{"Example":{"0.8.29":{"default":{"path":"Example.sol/Example.json","build_id":"4cb8066a7341661fda31173d8462bae1"}}}},"seenByCompiler":true}},"builds":["4cb8066a7341661fda31173d8462bae1"],"profiles":{"default":{"solc":{"optimizer":{"enabled":false,"runs":200},"metadata":{"useLiteralContent":false,"bytecodeHash":"ipfs","appendCBOR":true},"outputSelection":{"*":{"*":["abi","evm.bytecode.object","evm.bytecode.sourceMap","evm.bytecode.linkReferences","evm.deployedBytecode.object","evm.deployedBytecode.sourceMap","evm.deployedBytecode.linkReferences","evm.deployedBytecode.immutableReferences","evm.methodIdentifiers","metadata"]}},"evmVersion":"cancun","viaIR":false,"libraries":{}},"vyper":{"evmVersion":"cancun","outputSelection":{"*":{"*":["abi","evm.bytecode","evm.deployedBytecode"]}}}}},"preprocessed":false,"mocks":[]}